hadolintw/__init__.py
hadolintw/main.py
hadolintw-1.2.1.dist-info/entry_points.txt
hadolintw-1.2.1.dist-info/LICENSE
hadolintw-1.2.1.dist-info/WHEEL
hadolintw-1.2.1.dist-info/METADATA
hadolintw-1.2.1.dist-info/RECORD
