Metadata-Version: 2.1
Name: hadolintw
Version: 1.2.1
Summary: Pretty output for hadolint
Home-page: https://github.com/mperezi/hadolint-wrapper
License: MIT
Author: mperezi
Author-email: mperezibars@gmail.com
Requires-Python: >=3.6.0,<4.0.0
Classifier: License :: OSI Approved :: MIT License
Classifier: Programming Language :: Python :: 3
Classifier: Programming Language :: Python :: 3.6
Classifier: Programming Language :: Python :: 3.7
Classifier: Programming Language :: Python :: 3.8
Requires-Dist: click (>=5.0)
Project-URL: Repository, https://github.com/mperezi/hadolint-wrapper
